LICENSE
README.md
setup.py
learntools_dados_ufv/__init__.py
learntools_dados_ufv.egg-info/PKG-INFO
learntools_dados_ufv.egg-info/SOURCES.txt
learntools_dados_ufv.egg-info/dependency_links.txt
learntools_dados_ufv.egg-info/top_level.txt
learntools_dados_ufv.egg-info/zip-safe
learntools_dados_ufv/ccf425/__init__.py
learntools_dados_ufv/ccf425/pratica_1.py
learntools_dados_ufv/ccf425/pratica_10.py
learntools_dados_ufv/ccf425/pratica_2.py
learntools_dados_ufv/ccf425/pratica_3.py
learntools_dados_ufv/ccf425/pratica_5.py
learntools_dados_ufv/ccf425/pratica_7.py
learntools_dados_ufv/ccf425/pratica_7b.py
learntools_dados_ufv/ccf425/pratica_8.py
learntools_dados_ufv/ccf425/pratica_9.py
learntools_dados_ufv/ccf425/input/__init__.py
learntools_dados_ufv/core/__init__.py
learntools_dados_ufv/core/asserts.py
learntools_dados_ufv/core/colors.py
learntools_dados_ufv/core/constants.py
learntools_dados_ufv/core/exceptions.py
learntools_dados_ufv/core/globals_binder.py
learntools_dados_ufv/core/multiproblem.py
learntools_dados_ufv/core/problem.py
learntools_dados_ufv/core/problem_view.py
learntools_dados_ufv/core/richtext.py
learntools_dados_ufv/core/tracking.py
learntools_dados_ufv/core/utils.py