Metadata-Version: 2.1
Name: learntools-dados-ufv
Version: 1.0.11
Summary: Pacote auxiliar para correção e validação de práticas em dados
Home-page: http://github.com/gfviegas/learntools-dados-ufv
Author: Gustavo Viegas, Dan Becker
Author-email: gustavo.viegas@ufv.br
License: Apache 2.0
License-File: LICENSE
